csiparser.py
csiparser-0.1.0.dist-info/LICENSE
csiparser-0.1.0.dist-info/METADATA
csiparser-0.1.0.dist-info/WHEEL
csiparser-0.1.0.dist-info/top_level.txt
csiparser-0.1.0.dist-info/RECORD
