Metadata-Version: 2.1
Name: csiparser
Version: 0.1.0
Summary: A Python Package to Parse ESP32 Wi-Fi CSI Data
Home-page: https://github.com/RikeshMMM/ESP32-CSI-Python-Parser
Author: Rikesh Makwana
Author-email: rikesh.makwana@gmail.com
License: UNKNOWN
Platform: UNKNOWN
Requires-Dist: numpy (~=1.19.5)
Requires-Dist: pandas (~=1.2.3)
Provides-Extra: dev
Requires-Dist: pytest (>=3.7) ; extra == 'dev'
